data_xray/__init__.py
data_xray/file_io.py
data_xray/general_utilities.py
data_xray/modules.py
data_xray/cluster/__init__.py
data_xray/cluster/clusterviz.py
data_xray/cluster/core.py
data_xray/devel/__init__.py
data_xray/devel/dnd.py
data_xray/devel/legacy.py
data_xray/devel/dashviz/__init__.py
data_xray/devel/dashviz/test.py
data_xray/devel/htmldx/__init__.py
data_xray/devel/htmldx/core.py
data_xray/feature/__init__.py
data_xray/feature/core1D.py
data_xray/feature/core2D.py
data_xray/feature/itemize2D.py
data_xray/fileio/__init__.py
data_xray/fileio/gui_fname.py
data_xray/fit/__init__.py
data_xray/fit/bayes_emcee.py
data_xray/fit/bayes_pymc.py
data_xray/fit/core.py
data_xray/fit/fisher.py
data_xray/fit/fourier_t.py
data_xray/fit/injection.py
data_xray/fit/tunneling.py
data_xray/grid/__init__.py
data_xray/grid/core.py
data_xray/grid/dsops.py
data_xray/grid/gridviz.py
data_xray/htmldx/__init__.py
data_xray/htmldx/core.py
data_xray/nanonisio/__init__.py
data_xray/nanonisio/core.py
data_xray/pptdx/__init__.py
data_xray/pptdx/core.py
data_xray/qwant/__init__.py
data_xray/qwant/core.py
data_xray/report/__init__.py
data_xray/report/core.py
data_xray/scan/__init__.py
data_xray/scan/scanviz.py
data_xray/shared/__init__.py
data_xray/shared/ckpfm.py
data_xray/spectrum/__init__.py
data_xray/spectrum/core.py
data_xray/spectrum/specviz.py
data_xray/viz/__init__.py
data_xray/viz/clusterviz.py
data_xray/viz/core.py
data_xray/viz/gridviz.py
data_xray/viz/imageviz.py
data_xray/viz/specviz.py
data_xray/zones/__init__.py
data_xray/zones/grid_report.py
data_xray/zones/image_report.py
data_xray-0.2.0.dev0.dist-info/LICENSE.txt
data_xray-0.2.0.dev0.dist-info/METADATA
data_xray-0.2.0.dev0.dist-info/WHEEL
data_xray-0.2.0.dev0.dist-info/top_level.txt
data_xray-0.2.0.dev0.dist-info/RECORD
