Metadata-Version: 2.1
Name: data-xray
Version: 0.2.0.dev0
Summary: Pythonic cure for the common data problem
Home-page: https://bitbucket.org/glacio/data-xray
Author: Petro Maksymovych
Author-email: pmax20@gmail.com
Maintainer: Petro Maksymovych
Maintainer-email: pmax20@gmail.com
License: LICENSE.txt
Platform: UNKNOWN
Classifier: Development Status :: 4 - Beta
Classifier: License :: OSI Approved :: Apache Software License
Classifier: Topic :: Scientific/Engineering :: GIS
Classifier: Programming Language :: Python :: 3.5
Provides-Extra: docs
